hostz/__init__.py
hostz/_base_shell.py
hostz/_docker.py
hostz/_git.py
hostz/_go.py
hostz/_sed.py
hostz/_yaml.py
hostz/_zip.py
hostz/host.py
hostz/local.py
hostz-0.16.dist-info/LICENSE
hostz-0.16.dist-info/METADATA
hostz-0.16.dist-info/WHEEL
hostz-0.16.dist-info/top_level.txt
hostz-0.16.dist-info/zip-safe
hostz-0.16.dist-info/RECORD
