Metadata-Version: 2.1
Name: hostz
Version: 0.16
Summary: Easy use for operate remote host via ssh
Home-page: https://github.com/hanzhichao/hostz
Author: Han Zhichao
Author-email: superhin@126.com
License: MIT license
Keywords: hostz,ssh,sftp,ssh client
Classifier: Programming Language :: Python
Classifier: Programming Language :: Python :: 3.7
License-File: LICENSE
Requires-Dist: paramiko
Requires-Dist: paramiko-expect
Requires-Dist: logz
